{
  "manifestVersion": "3.2",
  "admin": {
    "address": "0xF4F152f35fF9579107d9055E019072B3E05da5b5",
    "txHash": "0x61e15bdfa51de901952d40a570a7f106a16e44e1d394e8c07348505dac340b59"
  },
  "proxies": [
    {
      "address": "0xaFFbDb406d41b9a1AFD041FeBD412A2dd236244C",
      "txHash": "0x92bf793d7e19e26bd89071d3a3013f04d27ea689343b8ed0e8be62d41786ce69",
      "kind": "transparent"
    },
    {
      "address": "0xF8F6F0C986B2dE4ABf1E8AAE12ffad3A376438D2",
      "txHash": "0xe439f9ad34b409ca4420bd0d3fbd2fd981214e12a71180f894bdc84adfe8b45b",
      "kind": "transparent"
    },
    {
      "address": "0x25748645193FD23102CEFE2f62Ea688E17afFBC5",
      "txHash": "0x21e70352e1dc7b41530c4af144016f3be2bef28a2b47e49594113aacfb7f88e8",
      "kind": "transparent"
    },
    {
      "address": "0x26083dD68999f46B79783DD25Fd2ed094ef7EAe8",
      "txHash": "0xc8d071f07618ba61b9f7c0be20683e373b56f0a9d69104c1683a6ba4c218edb6",
      "kind": "transparent"
    },
    {
      "address": "0x2e08D7A362a4d45Da76429a04E3DC6019E145794",
      "txHash": "0x6cfa1274a740188d16f9c2c3b3bcc7940280f18820ec4f243fa8436be8ddcbf6",
      "kind": "transparent"
    }
  ],
  "impls": {
    "d92fb78f80138eb4e85fc8dd461540bedd3623649823c74f27b0a298df03b7f9": {
      "address": "0x0B86B14E970c4462f6703Ba1DaF93Ec9EEeD92d0",
      "txHash": "0x80deffe7bdf6896dc9971ec6991f8f48def03532df7d5456eecc23244a4a4711",
      "layout": {
        "storage": [
          {
            "label": "_initialized",
            "offset": 0,
            "slot": "0",
            "type": "t_bool",
            "contract": "Initializable",
            "src": "@openzeppelin/contracts-upgradeable/proxy/utils/Initializable.sol:21"
          },
          {
            "label": "_initializing",
            "offset": 1,
            "slot": "0",
            "type": "t_bool",
            "contract": "Initializable",
            "src": "@openzeppelin/contracts-upgradeable/proxy/utils/Initializable.sol:26"
          },
          {
            "label": "__gap",
            "offset": 0,
            "slot": "1",
            "type": "t_array(t_uint256)50_storage",
            "contract": "ContextUpgradeable",
            "src": "@openzeppelin/contracts-upgradeable/utils/ContextUpgradeable.sol:30"
          },
          {
            "label": "_owner",
            "offset": 0,
            "slot": "51",
            "type": "t_address",
            "contract": "OwnableUpgradeable",
            "src": "@openzeppelin/contracts-upgradeable/access/OwnableUpgradeable.sol:21"
          },
          {
            "label": "__gap",
            "offset": 0,
            "slot": "52",
            "type": "t_array(t_uint256)49_storage",
            "contract": "OwnableUpgradeable",
            "src": "@openzeppelin/contracts-upgradeable/access/OwnableUpgradeable.sol:77"
          },
          {
            "label": "_status",
            "offset": 0,
            "slot": "101",
            "type": "t_uint256",
            "contract": "ReentrancyGuardUpgradeable",
            "src": "@openzeppelin/contracts-upgradeable/security/ReentrancyGuardUpgradeable.sol:37"
          },
          {
            "label": "__gap",
            "offset": 0,
            "slot": "102",
            "type": "t_array(t_uint256)49_storage",
            "contract": "ReentrancyGuardUpgradeable",
            "src": "@openzeppelin/contracts-upgradeable/security/ReentrancyGuardUpgradeable.sol:67"
          },
          {
            "label": "_paused",
            "offset": 0,
            "slot": "151",
            "type": "t_bool",
            "contract": "PausableUpgradeable",
            "src": "@openzeppelin/contracts-upgradeable/security/PausableUpgradeable.sol:28"
          },
          {
            "label": "__gap",
            "offset": 0,
            "slot": "152",
            "type": "t_array(t_uint256)49_storage",
            "contract": "PausableUpgradeable",
            "src": "@openzeppelin/contracts-upgradeable/security/PausableUpgradeable.sol:96"
          },
          {
            "label": "emptyArray",
            "offset": 0,
            "slot": "201",
            "type": "t_array(t_bytes32)64_storage",
            "contract": "Core",
            "src": "contracts/pool/Core.sol:22"
          },
          {
            "label": "_slippageParamK",
            "offset": 0,
            "slot": "265",
            "type": "t_uint256",
            "contract": "Pool",
            "src": "contracts/pool/Pool.sol:46"
          },
          {
            "label": "_slippageParamN",
            "offset": 0,
            "slot": "266",
            "type": "t_uint256",
            "contract": "Pool",
            "src": "contracts/pool/Pool.sol:47"
          },
          {
            "label": "_c1",
            "offset": 0,
            "slot": "267",
            "type": "t_uint256",
            "contract": "Pool",
            "src": "contracts/pool/Pool.sol:48"
          },
          {
            "label": "_xThreshold",
            "offset": 0,
            "slot": "268",
            "type": "t_uint256",
            "contract": "Pool",
            "src": "contracts/pool/Pool.sol:49"
          },
          {
            "label": "_haircutRate",
            "offset": 0,
            "slot": "269",
            "type": "t_uint256",
            "contract": "Pool",
            "src": "contracts/pool/Pool.sol:52"
          },
          {
            "label": "_retentionRatio",
            "offset": 0,
            "slot": "270",
            "type": "t_uint256",
            "contract": "Pool",
            "src": "contracts/pool/Pool.sol:55"
          },
          {
            "label": "_maxPriceDeviation",
            "offset": 0,
            "slot": "271",
            "type": "t_uint256",
            "contract": "Pool",
            "src": "contracts/pool/Pool.sol:59"
          },
          {
            "label": "_dev",
            "offset": 0,
            "slot": "272",
            "type": "t_address",
            "contract": "Pool",
            "src": "contracts/pool/Pool.sol:62"
          },
          {
            "label": "_priceOracle",
            "offset": 0,
            "slot": "273",
            "type": "t_contract(IPriceOracleGetter)5142",
            "contract": "Pool",
            "src": "contracts/pool/Pool.sol:65"
          },
          {
            "label": "_assets",
            "offset": 0,
            "slot": "274",
            "type": "t_struct(AssetMap)6697_storage",
            "contract": "Pool",
            "src": "contracts/pool/Pool.sol:68"
          }
        ],
        "types": {
          "t_address": {
            "label": "address",
            "numberOfBytes": "20"
          },
          "t_array(t_address)dyn_storage": {
            "label": "address[]",
            "numberOfBytes": "32"
          },
          "t_array(t_bytes32)64_storage": {
            "label": "bytes32[64]",
            "numberOfBytes": "2048"
          },
          "t_array(t_uint256)49_storage": {
            "label": "uint256[49]",
            "numberOfBytes": "1568"
          },
          "t_array(t_uint256)50_storage": {
            "label": "uint256[50]",
            "numberOfBytes": "1600"
          },
          "t_bool": {
            "label": "bool",
            "numberOfBytes": "1"
          },
          "t_bytes32": {
            "label": "bytes32",
            "numberOfBytes": "32"
          },
          "t_contract(Asset)4885": {
            "label": "contract Asset",
            "numberOfBytes": "20"
          },
          "t_contract(IPriceOracleGetter)5142": {
            "label": "contract IPriceOracleGetter",
            "numberOfBytes": "20"
          },
          "t_mapping(t_address,t_bool)": {
            "label": "mapping(address => bool)",
            "numberOfBytes": "32"
          },
          "t_mapping(t_address,t_contract(Asset)4885)": {
            "label": "mapping(address => contract Asset)",
            "numberOfBytes": "32"
          },
          "t_mapping(t_address,t_uint256)": {
            "label": "mapping(address => uint256)",
            "numberOfBytes": "32"
          },
          "t_struct(AssetMap)6697_storage": {
            "label": "struct Pool.AssetMap",
            "members": [
              {
                "label": "keys",
                "type": "t_array(t_address)dyn_storage",
                "offset": 0,
                "slot": "0"
              },
              {
                "label": "values",
                "type": "t_mapping(t_address,t_contract(Asset)4885)",
                "offset": 0,
                "slot": "1"
              },
              {
                "label": "indexOf",
                "type": "t_mapping(t_address,t_uint256)",
                "offset": 0,
                "slot": "2"
              },
              {
                "label": "inserted",
                "type": "t_mapping(t_address,t_bool)",
                "offset": 0,
                "slot": "3"
              }
            ],
            "numberOfBytes": "128"
          },
          "t_uint256": {
            "label": "uint256",
            "numberOfBytes": "32"
          }
        }
      }
    },
    "95e41e21c43c41020175592061735e5775c961616883e114fdcd613fb49bd138": {
      "address": "0xa6ae03Ff644156401205Afb6d241f245E3714F78",
      "txHash": "0x9b44f7134fb3fbe20bcb67149893ad485d4e88196a6d75044cea5ecf7319018b",
      "layout": {
        "storage": [
          {
            "label": "_initialized",
            "offset": 0,
            "slot": "0",
            "type": "t_bool",
            "contract": "Initializable",
            "src": "@openzeppelin/contracts-upgradeable/proxy/utils/Initializable.sol:21"
          },
          {
            "label": "_initializing",
            "offset": 1,
            "slot": "0",
            "type": "t_bool",
            "contract": "Initializable",
            "src": "@openzeppelin/contracts-upgradeable/proxy/utils/Initializable.sol:26"
          },
          {
            "label": "__gap",
            "offset": 0,
            "slot": "1",
            "type": "t_array(t_uint256)50_storage",
            "contract": "ContextUpgradeable",
            "src": "@openzeppelin/contracts-upgradeable/utils/ContextUpgradeable.sol:30"
          },
          {
            "label": "_owner",
            "offset": 0,
            "slot": "51",
            "type": "t_address",
            "contract": "OwnableUpgradeable",
            "src": "@openzeppelin/contracts-upgradeable/access/OwnableUpgradeable.sol:21"
          },
          {
            "label": "__gap",
            "offset": 0,
            "slot": "52",
            "type": "t_array(t_uint256)49_storage",
            "contract": "OwnableUpgradeable",
            "src": "@openzeppelin/contracts-upgradeable/access/OwnableUpgradeable.sol:77"
          },
          {
            "label": "accountName",
            "offset": 0,
            "slot": "101",
            "type": "t_string_storage",
            "contract": "AggregateAccount",
            "src": "contracts/asset/AggregateAccount.sol:15"
          },
          {
            "label": "isStable",
            "offset": 0,
            "slot": "102",
            "type": "t_bool",
            "contract": "AggregateAccount",
            "src": "contracts/asset/AggregateAccount.sol:19"
          }
        ],
        "types": {
          "t_address": {
            "label": "address",
            "numberOfBytes": "20"
          },
          "t_array(t_uint256)49_storage": {
            "label": "uint256[49]",
            "numberOfBytes": "1568"
          },
          "t_array(t_uint256)50_storage": {
            "label": "uint256[50]",
            "numberOfBytes": "1600"
          },
          "t_bool": {
            "label": "bool",
            "numberOfBytes": "1"
          },
          "t_string_storage": {
            "label": "string",
            "numberOfBytes": "32"
          },
          "t_uint256": {
            "label": "uint256",
            "numberOfBytes": "32"
          }
        }
      }
    },
    "224e9ea994ec0fc421bcc445ff834dea7966579f9428fe68606fd579cb803983": {
      "address": "0xFE0401CeCBfDA864cAE84F8e716B71e32eD405aE",
      "txHash": "0x730006d9123c12abea93a9d70e5c440cf78357f65e6fb17d8498839050cd1c04",
      "layout": {
        "storage": [
          {
            "label": "_initialized",
            "offset": 0,
            "slot": "0",
            "type": "t_bool",
            "contract": "Initializable",
            "src": "@openzeppelin/contracts-upgradeable/proxy/utils/Initializable.sol:21"
          },
          {
            "label": "_initializing",
            "offset": 1,
            "slot": "0",
            "type": "t_bool",
            "contract": "Initializable",
            "src": "@openzeppelin/contracts-upgradeable/proxy/utils/Initializable.sol:26"
          },
          {
            "label": "__gap",
            "offset": 0,
            "slot": "1",
            "type": "t_array(t_uint256)50_storage",
            "contract": "ContextUpgradeable",
            "src": "@openzeppelin/contracts-upgradeable/utils/ContextUpgradeable.sol:30"
          },
          {
            "label": "_owner",
            "offset": 0,
            "slot": "51",
            "type": "t_address",
            "contract": "OwnableUpgradeable",
            "src": "@openzeppelin/contracts-upgradeable/access/OwnableUpgradeable.sol:21"
          },
          {
            "label": "__gap",
            "offset": 0,
            "slot": "52",
            "type": "t_array(t_uint256)49_storage",
            "contract": "OwnableUpgradeable",
            "src": "@openzeppelin/contracts-upgradeable/access/OwnableUpgradeable.sol:77"
          },
          {
            "label": "_balances",
            "offset": 0,
            "slot": "101",
            "type": "t_mapping(t_address,t_uint256)",
            "contract": "ERC20Upgradeable",
            "src": "@openzeppelin/contracts-upgradeable/token/ERC20/ERC20Upgradeable.sol:36"
          },
          {
            "label": "_allowances",
            "offset": 0,
            "slot": "102",
            "type": "t_mapping(t_address,t_mapping(t_address,t_uint256))",
            "contract": "ERC20Upgradeable",
            "src": "@openzeppelin/contracts-upgradeable/token/ERC20/ERC20Upgradeable.sol:38"
          },
          {
            "label": "_totalSupply",
            "offset": 0,
            "slot": "103",
            "type": "t_uint256",
            "contract": "ERC20Upgradeable",
            "src": "@openzeppelin/contracts-upgradeable/token/ERC20/ERC20Upgradeable.sol:40"
          },
          {
            "label": "_name",
            "offset": 0,
            "slot": "104",
            "type": "t_string_storage",
            "contract": "ERC20Upgradeable",
            "src": "@openzeppelin/contracts-upgradeable/token/ERC20/ERC20Upgradeable.sol:42"
          },
          {
            "label": "_symbol",
            "offset": 0,
            "slot": "105",
            "type": "t_string_storage",
            "contract": "ERC20Upgradeable",
            "src": "@openzeppelin/contracts-upgradeable/token/ERC20/ERC20Upgradeable.sol:43"
          },
          {
            "label": "__gap",
            "offset": 0,
            "slot": "106",
            "type": "t_array(t_uint256)45_storage",
            "contract": "ERC20Upgradeable",
            "src": "@openzeppelin/contracts-upgradeable/token/ERC20/ERC20Upgradeable.sol:361"
          },
          {
            "label": "_underlyingToken",
            "offset": 0,
            "slot": "151",
            "type": "t_address",
            "contract": "Asset",
            "src": "contracts/asset/Asset.sol:22"
          },
          {
            "label": "_pool",
            "offset": 0,
            "slot": "152",
            "type": "t_address",
            "contract": "Asset",
            "src": "contracts/asset/Asset.sol:24"
          },
          {
            "label": "_cash",
            "offset": 0,
            "slot": "153",
            "type": "t_uint256",
            "contract": "Asset",
            "src": "contracts/asset/Asset.sol:26"
          },
          {
            "label": "_liability",
            "offset": 0,
            "slot": "154",
            "type": "t_uint256",
            "contract": "Asset",
            "src": "contracts/asset/Asset.sol:28"
          },
          {
            "label": "_owner",
            "offset": 0,
            "slot": "155",
            "type": "t_address",
            "contract": "Asset",
            "src": "contracts/asset/Asset.sol:30"
          },
          {
            "label": "_aggregateAccount",
            "offset": 0,
            "slot": "156",
            "type": "t_address",
            "contract": "Asset",
            "src": "contracts/asset/Asset.sol:32"
          },
          {
            "label": "_maxSupply",
            "offset": 0,
            "slot": "157",
            "type": "t_uint256",
            "contract": "Asset",
            "src": "contracts/asset/Asset.sol:35"
          }
        ],
        "types": {
          "t_address": {
            "label": "address",
            "numberOfBytes": "20"
          },
          "t_array(t_uint256)45_storage": {
            "label": "uint256[45]",
            "numberOfBytes": "1440"
          },
          "t_array(t_uint256)49_storage": {
            "label": "uint256[49]",
            "numberOfBytes": "1568"
          },
          "t_array(t_uint256)50_storage": {
            "label": "uint256[50]",
            "numberOfBytes": "1600"
          },
          "t_bool": {
            "label": "bool",
            "numberOfBytes": "1"
          },
          "t_mapping(t_address,t_mapping(t_address,t_uint256))": {
            "label": "mapping(address => mapping(address => uint256))",
            "numberOfBytes": "32"
          },
          "t_mapping(t_address,t_uint256)": {
            "label": "mapping(address => uint256)",
            "numberOfBytes": "32"
          },
          "t_string_storage": {
            "label": "string",
            "numberOfBytes": "32"
          },
          "t_uint256": {
            "label": "uint256",
            "numberOfBytes": "32"
          }
        }
      }
    }
  }
}
